complexity_tokenizer/__init__.py
complexity_tokenizer/complexity_tokenizer.cpython-310-x86_64-linux-gnu.so
complexity_tokenizer-0.3.3.dist-info/METADATA
complexity_tokenizer-0.3.3.dist-info/WHEEL
complexity_tokenizer-0.3.3.dist-info/RECORD
