Metadata-Version: 2.4
Name: complexity-tokenizer
Version: 0.3.3
Classifier: Development Status :: 4 - Beta
Classifier: Intended Audience :: Developers
Classifier: Intended Audience :: Science/Research
Classifier: License :: OSI Approved :: Apache Software License
Classifier: Programming Language :: Python :: 3
Classifier: Programming Language :: Python :: 3.8
Classifier: Programming Language :: Python :: 3.9
Classifier: Programming Language :: Python :: 3.10
Classifier: Programming Language :: Python :: 3.11
Classifier: Programming Language :: Python :: 3.12
Classifier: Programming Language :: Rust
Classifier: Topic :: Scientific/Engineering :: Artificial Intelligence
Classifier: Topic :: Text Processing :: Linguistic
Requires-Dist: numpy>=1.20
Requires-Dist: pytest>=7.0 ; extra == 'dev'
Requires-Dist: maturin>=1.4 ; extra == 'dev'
Provides-Extra: dev
Summary: Fast BPE tokenizer in Rust with HuggingFace compatibility
Keywords: tokenizer,bpe,nlp,huggingface,rust,fast
Author-email: Complexity-ML <contact@complexity-ml.org>
License: Apache-2.0
Requires-Python: >=3.8
Project-URL: Documentation, https://github.com/Complexity-ML/complexity-tokenizer#readme
Project-URL: Homepage, https://github.com/Complexity-ML/complexity-tokenizer
Project-URL: Repository, https://github.com/Complexity-ML/complexity-tokenizer
